pg_partition/__init__.py
pg_partition/date_partition_util.py
pg_partition/pg_connection.py
pg_partition/pg_partition.py
src/date_partition_util.py
src/pg_connection.py
src/pg_partition.py
datapunt_pg_partitioning-2019.2.27.3.dist-info/LICENSE.rst
datapunt_pg_partitioning-2019.2.27.3.dist-info/METADATA
datapunt_pg_partitioning-2019.2.27.3.dist-info/WHEEL
datapunt_pg_partitioning-2019.2.27.3.dist-info/entry_points.txt
datapunt_pg_partitioning-2019.2.27.3.dist-info/top_level.txt
datapunt_pg_partitioning-2019.2.27.3.dist-info/RECORD
