Metadata-Version: 2.1
Name: datapunt-pg-partitioning
Version: 2019.2.27.3
Summary: Datapunt Amsterdam postgres table partitioning module
Home-page: https://github.com/amsterdam/pg_partition
Author: Datapunt Amsterdam
Author-email: datapunt@amsterdam.nl
License: Mozilla Public License Version 2.0
Platform: UNKNOWN
Classifier: Development Status :: 3 - Alpha
Classifier: Intended Audience :: Developers
Classifier: Natural Language :: English
Classifier: Programming Language :: Python
Classifier: Programming Language :: Python :: 3.6
Classifier: License :: OSI Approved :: Mozilla Public License 2.0 (MPL 2.0)
Requires-Dist: psycopg2-binary
Requires-Dist: python-dateutil
Provides-Extra: dev
Requires-Dist: pytest ; extra == 'dev'
Requires-Dist: pytest-cov ; extra == 'dev'
Requires-Dist: pylint ; extra == 'dev'
Requires-Dist: twine ; extra == 'dev'
Provides-Extra: docs
Requires-Dist: sphinx ; extra == 'docs'
Requires-Dist: sphinx-autobuild ; extra == 'docs'
Requires-Dist: sphinx-rtd-theme ; extra == 'docs'
